<annotation verified="yes">
	<folder>imagesHat</folder>
	<filename>202. 0b151545-c769-4517-9c05-78f2ef042739-usatsi_11152154.jpg</filename>
	<path>~/hat-detector/data/images/202. 0b151545-c769-4517-9c05-78f2ef042739-usatsi_11152154.jpg</path>
	<source>
		<database>Unknown</database>
	</source>
	<size>
		<width>2950</width>
		<height>1680</height>
		<depth>3</depth>
	</size>
	<segmented>0</segmented>
	<object>
		<name>hat	</name>
		<pose>Unspecified</pose>
		<truncated>0</truncated>
		<difficult>0</difficult>
		<bndbox>
			<xmin>1037</xmin>
			<ymin>129</ymin>
			<xmax>1735</xmax>
			<ymax>494</ymax>
		</bndbox>
	</object>
</annotation>