<annotation verified="yes">
	<folder>imagesHat</folder>
	<filename>28. trucker-hat-mens-street-style.jpg</filename>
	<path>~/hat-detector/data/images/28. trucker-hat-mens-street-style.jpg</path>
	<source>
		<database>Unknown</database>
	</source>
	<size>
		<width>770</width>
		<height>970</height>
		<depth>3</depth>
	</size>
	<segmented>0</segmented>
	<object>
		<name>hat	</name>
		<pose>Unspecified</pose>
		<truncated>0</truncated>
		<difficult>0</difficult>
		<bndbox>
			<xmin>283</xmin>
			<ymin>19</ymin>
			<xmax>488</xmax>
			<ymax>152</ymax>
		</bndbox>
	</object>
</annotation>