<annotation verified="yes">
	<folder>imagesHat</folder>
	<filename>415. bng-l-as-1004-16.jpg</filename>
	<path>~/hat-detector/data/images/415. bng-l-as-1004-16.jpg</path>
	<source>
		<database>Unknown</database>
	</source>
	<size>
		<width>620</width>
		<height>450</height>
		<depth>3</depth>
	</size>
	<segmented>0</segmented>
	<object>
		<name>hat	</name>
		<pose>Unspecified</pose>
		<truncated>0</truncated>
		<difficult>0</difficult>
		<bndbox>
			<xmin>213</xmin>
			<ymin>143</ymin>
			<xmax>523</xmax>
			<ymax>315</ymax>
		</bndbox>
	</object>
</annotation>