<annotation verified="yes">
	<folder>imagesHat</folder>
	<filename>424. osf-apparel-man-women-portland-1-1200x664.jpg</filename>
	<path>~/hat-detector/data/images/424. osf-apparel-man-women-portland-1-1200x664.jpg</path>
	<source>
		<database>Unknown</database>
	</source>
	<size>
		<width>1200</width>
		<height>664</height>
		<depth>3</depth>
	</size>
	<segmented>0</segmented>
	<object>
		<name>hat	</name>
		<pose>Unspecified</pose>
		<truncated>0</truncated>
		<difficult>0</difficult>
		<bndbox>
			<xmin>258</xmin>
			<ymin>105</ymin>
			<xmax>465</xmax>
			<ymax>218</ymax>
		</bndbox>
	</object>
</annotation>