<annotation verified="yes">
	<folder>imagesHat</folder>
	<filename>442. 1fc2d9373da6f934b755a0bed38cf4a5--baseball-caps-baseball-cap-short-hair.jpg</filename>
	<path>~/hat-detector/data/images/442. 1fc2d9373da6f934b755a0bed38cf4a5--baseball-caps-baseball-cap-short-hair.jpg</path>
	<source>
		<database>Unknown</database>
	</source>
	<size>
		<width>236</width>
		<height>454</height>
		<depth>3</depth>
	</size>
	<segmented>0</segmented>
	<object>
		<name>hat	</name>
		<pose>Unspecified</pose>
		<truncated>0</truncated>
		<difficult>0</difficult>
		<bndbox>
			<xmin>91</xmin>
			<ymin>10</ymin>
			<xmax>165</xmax>
			<ymax>58</ymax>
		</bndbox>
	</object>
</annotation>