<annotation verified="yes">
	<folder>imagesHat</folder>
	<filename>481. jim_bouton_1969.jpg</filename>
	<path>~/hat-detector/data/images/481. jim_bouton_1969.jpg</path>
	<source>
		<database>Unknown</database>
	</source>
	<size>
		<width>359</width>
		<height>424</height>
		<depth>1</depth>
	</size>
	<segmented>0</segmented>
	<object>
		<name>hat	</name>
		<pose>Unspecified</pose>
		<truncated>0</truncated>
		<difficult>0</difficult>
		<bndbox>
			<xmin>70</xmin>
			<ymin>4</ymin>
			<xmax>296</xmax>
			<ymax>137</ymax>
		</bndbox>
	</object>
</annotation>