<annotation verified="yes">
	<folder>Hat Images</folder>
	<filename>56. portrait-of-a-young-woman-wearing-basketball-cap-looking-away-f0w5x1.jpg</filename>
	<path>~/hat-detector/data/images/56. portrait-of-a-young-woman-wearing-basketball-cap-looking-away-f0w5x1.jpg</path>
	<source>
		<database>Unknown</database>
	</source>
	<size>
		<width>1300</width>
		<height>956</height>
		<depth>3</depth>
	</size>
	<segmented>0</segmented>
	<object>
		<name>hat</name>
		<pose>Unspecified</pose>
		<truncated>0</truncated>
		<difficult>0</difficult>
		<bndbox>
			<xmin>525</xmin>
			<ymin>73</ymin>
			<xmax>851</xmax>
			<ymax>220</ymax>
		</bndbox>
	</object>
</annotation>