<annotation verified="yes">
	<folder>Hat Images</folder>
	<filename>90. mark_hager_head_coach_gb__england_womens_hockey_jan_2019.jpg</filename>
	<path>~/hat-detector/data/images/90. mark_hager_head_coach_gb__england_womens_hockey_jan_2019.jpg</path>
	<source>
		<database>Unknown</database>
	</source>
	<size>
		<width>1000</width>
		<height>656</height>
		<depth>3</depth>
	</size>
	<segmented>0</segmented>
	<object>
		<name>hat</name>
		<pose>Unspecified</pose>
		<truncated>0</truncated>
		<difficult>0</difficult>
		<bndbox>
			<xmin>281</xmin>
			<ymin>2</ymin>
			<xmax>824</xmax>
			<ymax>267</ymax>
		</bndbox>
	</object>
</annotation>